importtime_waterfall.py
importtime_waterfall-1.0.0.dist-info/LICENSE
importtime_waterfall-1.0.0.dist-info/METADATA
importtime_waterfall-1.0.0.dist-info/WHEEL
importtime_waterfall-1.0.0.dist-info/entry_points.txt
importtime_waterfall-1.0.0.dist-info/top_level.txt
importtime_waterfall-1.0.0.dist-info/RECORD
