Metadata-Version: 2.1
Name: importtime-waterfall
Version: 1.0.0
Summary: Generate waterfalls from `-Ximporttime` tracing.
Home-page: https://github.com/asottile/importtime-waterfall
Author: Anthony Sottile
Author-email: asottile@umich.edu
License: MIT
Platform: UNKNOWN
Classifier: License :: OSI Approved :: MIT License
Classifier: Programming Language :: Python :: 3
Classifier: Programming Language :: Python :: 3 :: Only
Classifier: Programming Language :: Python :: 3.7
Classifier: Programming Language :: Python :: Implementation :: CPython
Requires-Python: >=3.7
